{
	"adjectives":[
		"smart",
		"great",
		"alone",
		"small",
		"large"
	],
	"food":[
		"salad",
		"kebab",
		"apple",
		"bread",
		"cream",
		"fruit",
		"lunch",
		"sugar"
	],
	"vehicles":[
		"plane",
		"metro",
		"pilot",
		"motor",
		"drive"
	],
	"drinks":[
		"vodka",
		"water",
		"drink"
	],
	"animals":[
		"rhino",
		"horse",
		"sheep"
	],
	"places":[
		"beach",
		"class",
		"store",
		"coast",
		"field",
		"place",
		"hotel",
		"house"
	],
	"colors":[
		"black",
		"brown",
		"green",
		"white",
		"color"
	],
	"countries":[
		"china",
		"japan"
	]
}